Metadata-Version: 1.0
Name: figaria
Version: 1.0.2
Summary: Pakiet testowy
Home-page: http://tekst.pl
Author: UNKNOWN
Author-email: UNKNOWN
License: UNKNOWN
Platform: UNKNOWN
